yao_utils/__init__.py
yao_utils/yao_uuid.py
yao_utils-0.0.2.dist-info/METADATA
yao_utils-0.0.2.dist-info/WHEEL
yao_utils-0.0.2.dist-info/top_level.txt
yao_utils-0.0.2.dist-info/RECORD
