Metadata-Version: 2.1
Name: yao_utils
Version: 0.0.2
Summary: 我的工具包
Author: Yaohoohi
Author-email: yaohoohi@qq.com
License: MIT
Requires-Dist: uuid
